{
  "tasks": [
    {
      "id": "2",
      "text": "Meeting",
      "year": "2023",
      "month": "July ",
      "day": "21",
      "time": "10am",
      "reminder": true
    },
    {
      "id": "3",
      "text": "GYM",
      "year": "2023",
      "month": "August",
      "day": " 01",
      "time": "11pm",
      "reminder": true
    },
    {
      "id": "e065",
      "text": "sadfsg",
      "day": "fbdgf",
      "month": "dfgdhg",
      "year": "fbgn",
      "reminder": "",
      "time": "dfdbgf"
    }
  ]
}